README.md
setup.cfg
setup.py
reportng/__init__.py
reportng/__version__.py
reportng/core.py
reportng/rnghelpers.py
reportng/rngtypes.py
reportng.egg-info/PKG-INFO
reportng.egg-info/SOURCES.txt
reportng.egg-info/dependency_links.txt
reportng.egg-info/requires.txt
reportng.egg-info/top_level.txt