Metadata-Version: 1.2
Name: reportng
Version: 1.0.1
Summary: reportng is a simple python module that allows one to create beautiful yet simple Bootstrap 4 html reports. Reportng is capable of working with any string types output that is generated by python.
Home-page: https://github.com/securisec/reportng
Author: Hapsida @securisec
Author-email: 
License: UNKNOWN
Keywords: report,reporting,bootstrap
Platform: UNKNOWN
Classifier: Programming Language :: Python :: 3.6
Classifier: Programming Language :: Python :: 3.7
Classifier: Programming Language :: Python :: 3.8
Classifier: Programming Language :: Python :: Implementation :: PyPy
Classifier: Natural Language :: English
Requires-Python: >=3.6
